executable/__init__.py
executable/__main__.py
executable/cli.exe
executable/cli.py
executable/py.typed
executable-0.1.0.dist-info/LICENSE
executable-0.1.0.dist-info/METADATA
executable-0.1.0.dist-info/WHEEL
executable-0.1.0.dist-info/entry_points.txt
executable-0.1.0.dist-info/top_level.txt
executable-0.1.0.dist-info/RECORD
